morph_kgc/__init__.py
morph_kgc/__main__.py
morph_kgc/_version.py
morph_kgc/args_parser.py
morph_kgc/config.py
morph_kgc/constants.py
morph_kgc/materializer.py
morph_kgc/utils.py
morph_kgc/data_source/__init__.py
morph_kgc/data_source/data_file.py
morph_kgc/data_source/http_api.py
morph_kgc/data_source/property_graph_db.py
morph_kgc/data_source/python_data.py
morph_kgc/data_source/relational_db.py
morph_kgc/fnml/__init__.py
morph_kgc/fnml/built_in_functions.py
morph_kgc/fnml/fnml_executer.py
morph_kgc/fnml/grel/array_functions.py
morph_kgc/fnml/grel/control_functions.py
morph_kgc/fnml/grel/date_functions.py
morph_kgc/fnml/grel/math_functions.py
morph_kgc/fnml/grel/other_functions.py
morph_kgc/fnml/grel/string_functions.py
morph_kgc/mapping/__init__.py
morph_kgc/mapping/mapping_constants.py
morph_kgc/mapping/mapping_parser.py
morph_kgc/mapping/mapping_partitioner.py
morph_kgc/mapping/yarrrml.py
morph_kgc-2.10.0.dist-info/METADATA
morph_kgc-2.10.0.dist-info/WHEEL
morph_kgc-2.10.0.dist-info/licenses/LICENSE
morph_kgc-2.10.0.dist-info/RECORD
