Metadata-Version: 2.4
Name: morph_kgc
Version: 2.10.0
Summary: Powerful [R2]RML engine to create RDF knowledge graphs from heterogeneous data sources.
Project-URL: Documentation, https://morph-kgc.readthedocs.io
Project-URL: Source, https://github.com/morph-kgc/morph-kgc
Project-URL: Tracker, https://github.com/morph-kgc/morph-kgc/issues
Project-URL: CI, https://github.com/morph-kgc/morph-kgc/actions
Project-URL: Homepage, https://morph-kgc.readthedocs.io
Project-URL: History, https://github.com/morph-kgc/morph-kgc/releases
Author-email: Julián Arenas-Guerrero <julian.arenas.guerrero@upm.es>
License-Expression: Apache-2.0
License-File: LICENSE
Keywords: Data Integration,Knowledge Graph,Morph-KGC,R2RML,RDF,RML,RML-star
Classifier: Development Status :: 5 - Production/Stable
Classifier: Environment :: Console
Classifier: Intended Audience :: Information Technology
Classifier: Intended Audience :: Science/Research
Classifier: License :: OSI Approved :: Apache Software License
Classifier: Operating System :: OS Independent
Classifier: Programming Language :: Python :: 3
Classifier: Programming Language :: Python :: 3.10
Classifier: Programming Language :: Python :: 3.11
Classifier: Programming Language :: Python :: 3.12
Classifier: Programming Language :: Python :: 3.13
Classifier: Topic :: Database
Classifier: Topic :: Scientific/Engineering :: Interface Engine/Protocol Translator
Classifier: Topic :: Software Development :: Pre-processors
Classifier: Topic :: Utilities
Requires-Python: >=3.9
Requires-Dist: duckdb<2.0.0,>=1.0.0
Requires-Dist: elementpath<5.0.0,>=4.0.0
Requires-Dist: falcon<5.0.0,>=3.0.0
Requires-Dist: jsonpath-python==1.0.6
Requires-Dist: pandas<3.0.0,>=2.1.0
Requires-Dist: pyoxigraph<0.4.0,>=0.3.0
Requires-Dist: rdflib<7.3.0,>=6.1.1
Requires-Dist: ruamel-yaml<0.19.0,>=0.18.0
Provides-Extra: all
Requires-Dist: cryptography<43.0.0,>=42.0.0; extra == 'all'
Requires-Dist: databricks-sqlalchemy<3.0.0,>=2.0.4; extra == 'all'
Requires-Dist: geopandas<2.0.0,>=1.0.0; extra == 'all'
Requires-Dist: kafka-python<3.0.0,>=2.0.2; extra == 'all'
Requires-Dist: kuzu<2.0.0,>=0.4.2; extra == 'all'
Requires-Dist: neo4j<6.0.0,>=5.20.0; extra == 'all'
Requires-Dist: odfpy<2.0.0,>=1.4.1; extra == 'all'
Requires-Dist: openpyxl<4.0.0,>=3.0.0; extra == 'all'
Requires-Dist: oracledb<9.0.0,>=2.5.0; extra == 'all'
Requires-Dist: psycopg[binary]<4.0.0,>=3.0.0; extra == 'all'
Requires-Dist: pyarrow<16.0.0,>=14.0.0; extra == 'all'
Requires-Dist: pyjelly>=0.6.2; extra == 'all'
Requires-Dist: pymssql<3.0.0,>=2.2.7; extra == 'all'
Requires-Dist: pymysql<2.0.0,>=1.1.0; extra == 'all'
Requires-Dist: pyreadstat<2.0.0,>=1.2.0; extra == 'all'
Requires-Dist: requests<3.0.0,>=2.0.0; extra == 'all'
Requires-Dist: snowflake-sqlalchemy<2.0.0,>=1.7.3; extra == 'all'
Requires-Dist: sql-metadata<3.0.0,>=2.6.0; extra == 'all'
Requires-Dist: sqlalchemy<3.0.0,>=2.0.0; extra == 'all'
Provides-Extra: databricks
Requires-Dist: databricks-sqlalchemy<3.0.0,>=2.0.4; extra == 'databricks'
Provides-Extra: excel
Requires-Dist: odfpy<2.0.0,>=1.4.1; extra == 'excel'
Requires-Dist: openpyxl<4.0.0,>=3.0.0; extra == 'excel'
Provides-Extra: geoparquet
Requires-Dist: geopandas<2.0.0,>=1.0.0; extra == 'geoparquet'
Provides-Extra: http
Requires-Dist: requests<3.0.0,>=2.0.0; extra == 'http'
Provides-Extra: jelly
Requires-Dist: pyjelly>=0.6.2; extra == 'jelly'
Provides-Extra: kafka
Requires-Dist: kafka-python<3.0.0,>=2.0.2; extra == 'kafka'
Provides-Extra: kuzu
Requires-Dist: kuzu<2.0.0,>=0.4.2; extra == 'kuzu'
Provides-Extra: mssql
Requires-Dist: pymssql<3.0.0,>=2.2.7; extra == 'mssql'
Requires-Dist: sql-metadata<3.0.0,>=2.6.0; extra == 'mssql'
Requires-Dist: sqlalchemy<3.0.0,>=2.0.0; extra == 'mssql'
Provides-Extra: mysql
Requires-Dist: cryptography<43.0.0,>=42.0.0; extra == 'mysql'
Requires-Dist: pymysql<2.0.0,>=1.1.0; extra == 'mysql'
Requires-Dist: sql-metadata<3.0.0,>=2.6.0; extra == 'mysql'
Requires-Dist: sqlalchemy<3.0.0,>=2.0.0; extra == 'mysql'
Provides-Extra: neo4j
Requires-Dist: neo4j<6.0.0,>=5.20.0; extra == 'neo4j'
Provides-Extra: oracle
Requires-Dist: oracledb<9.0.0,>=2.5.0; extra == 'oracle'
Requires-Dist: sql-metadata<3.0.0,>=2.6.0; extra == 'oracle'
Requires-Dist: sqlalchemy<3.0.0,>=2.0.0; extra == 'oracle'
Provides-Extra: postgresql
Requires-Dist: psycopg[binary]<4.0.0,>=3.0.0; extra == 'postgresql'
Requires-Dist: sql-metadata<3.0.0,>=2.6.0; extra == 'postgresql'
Requires-Dist: sqlalchemy<3.0.0,>=2.0.0; extra == 'postgresql'
Provides-Extra: snowflake
Requires-Dist: snowflake-sqlalchemy<2.0.0,>=1.7.3; extra == 'snowflake'
Provides-Extra: spss
Requires-Dist: pyreadstat<2.0.0,>=1.2.0; extra == 'spss'
Provides-Extra: sqlite
Requires-Dist: sql-metadata<3.0.0,>=2.6.0; extra == 'sqlite'
Requires-Dist: sqlalchemy<3.0.0,>=2.0.0; extra == 'sqlite'
Provides-Extra: tabular
Requires-Dist: pyarrow<16.0.0,>=14.0.0; extra == 'tabular'
Provides-Extra: test
Requires-Dist: geopandas<2.0.0,>=1.0.0; extra == 'test'
Requires-Dist: odfpy<2.0.0,>=1.4.1; extra == 'test'
Requires-Dist: openpyxl<4.0.0,>=3.0.0; extra == 'test'
Requires-Dist: pyarrow<20.0.0,>=14.0.0; extra == 'test'
Requires-Dist: pytest<9.0.0,>=8.0.0; extra == 'test'
Requires-Dist: sql-metadata<3.0.0,>=2.6.0; extra == 'test'
Requires-Dist: sqlalchemy<3.0.0,>=2.0.0; extra == 'test'
